python_terraform_bridge/__init__.py
python_terraform_bridge/__main__.py
python_terraform_bridge/cli.py
python_terraform_bridge/module_resources.py
python_terraform_bridge/parameter.py
python_terraform_bridge/py.typed
python_terraform_bridge/registry.py
python_terraform_bridge/runtime.py
python_terraform_bridge-0.1.1.dist-info/METADATA
python_terraform_bridge-0.1.1.dist-info/WHEEL
python_terraform_bridge-0.1.1.dist-info/entry_points.txt
python_terraform_bridge-0.1.1.dist-info/RECORD
