Metadata-Version: 2.4
Name: python-terraform-bridge
Version: 0.1.1
Summary: Bridge Python classes to Terraform external data sources and modules
Project-URL: Homepage, https://github.com/jbcom/python-terraform-bridge
Project-URL: Repository, https://github.com/jbcom/python-terraform-bridge
Project-URL: Documentation, https://github.com/jbcom/python-terraform-bridge#readme
Author-email: Jon Bogaty <jon@jonbogaty.com>
Maintainer-email: Jon Bogaty <jon@jonbogaty.com>
License: MIT
Keywords: bridge,code-generation,external-data,iac,infrastructure,terraform
Classifier: Development Status :: 4 - Beta
Classifier: Intended Audience :: Developers
Classifier: License :: OSI Approved :: MIT License
Classifier: Operating System :: OS Independent
Classifier: Programming Language :: Python :: 3
Classifier: Programming Language :: Python :: 3.9
Classifier: Programming Language :: Python :: 3.10
Classifier: Programming Language :: Python :: 3.11
Classifier: Programming Language :: Python :: 3.12
Classifier: Programming Language :: Python :: 3.13
Classifier: Topic :: Software Development :: Code Generators
Classifier: Topic :: System :: Systems Administration
Classifier: Typing :: Typed
Requires-Python: >=3.9
Requires-Dist: directed-inputs-class>=202511.3.0
Requires-Dist: extended-data-types>=202511.8.0
Requires-Dist: lifecyclelogging>=202511.3.0
Requires-Dist: tssplit>=0.1.1
Provides-Extra: dev
Requires-Dist: pytest-cov>=4.1.0; extra == 'dev'
Requires-Dist: pytest>=8.0.0; extra == 'dev'
Requires-Dist: ruff>=0.8.0; extra == 'dev'
Provides-Extra: tests
Requires-Dist: pytest-cov>=4.1.0; extra == 'tests'
Requires-Dist: pytest>=8.0.0; extra == 'tests'
